deepdog/__init__.py
deepdog/cli/__init__.py
deepdog/cli/probs/__init__.py
deepdog/cli/probs/args.py
deepdog/cli/probs/dicts.py
deepdog/cli/probs/main.py
deepdog/cli/subset_sim_probs/__init__.py
deepdog/cli/subset_sim_probs/args.py
deepdog/cli/subset_sim_probs/dicts.py
deepdog/cli/subset_sim_probs/main.py
deepdog/cli/util/__init__.py
deepdog/cli/util/confirm.py
deepdog/direct_monte_carlo/__init__.py
deepdog/direct_monte_carlo/compose_filter.py
deepdog/direct_monte_carlo/cost_function_filter.py
deepdog/direct_monte_carlo/direct_mc.py
deepdog/direct_monte_carlo/dmc_filters.py
deepdog/indexify/__init__.py
deepdog/meta.py
deepdog/real_spectrum_run.py
deepdog/results/__init__.py
deepdog/results/filename.py
deepdog/results/read_csv.py
deepdog/subset_simulation/__init__.py
deepdog/subset_simulation/subset_simulation_impl.py
deepdog/temp_aware_real_spectrum_run.py
deepdog-1.7.0.dist-info/METADATA
deepdog-1.7.0.dist-info/WHEEL
deepdog-1.7.0.dist-info/entry_points.txt
deepdog-1.7.0.dist-info/RECORD
