Metadata-Version: 2.1
Name: deepdog
Version: 1.7.0
Summary: 
Author: Deepak Mallubhotla
Author-email: dmallubhotla+github@gmail.com
Requires-Python: >=3.8.1,<3.10
Classifier: Programming Language :: Python :: 3
Classifier: Programming Language :: Python :: 3.9
Requires-Dist: numpy (==1.22.3)
Requires-Dist: pdme (>=1.5.0,<2.0.0)
Requires-Dist: scipy (==1.10)
Requires-Dist: tqdm (>=4.66.2,<5.0.0)
